transform/__init__.py
transform/auth.py
transform/cli/__init__.py
transform/cli/cli_context.py
transform/cli/cli_utils.py
transform/cli/mql_cli.py
transform/constants.py
transform/exceptions.py
transform/helpers.py
transform/interfaces.py
transform/models.py
transform/mql.py
transform/utils.py
transform/vendor/gql/__init__.py
transform/vendor/gql/__version__.py
transform/vendor/gql/cli.py
transform/vendor/gql/client.py
transform/vendor/gql/dsl.py
transform/vendor/gql/gql.py
transform/vendor/gql/py.typed
transform/vendor/gql/transport/__init__.py
transform/vendor/gql/transport/aiohttp.py
transform/vendor/gql/transport/appsync_auth.py
transform/vendor/gql/transport/appsync_websockets.py
transform/vendor/gql/transport/async_transport.py
transform/vendor/gql/transport/exceptions.py
transform/vendor/gql/transport/local_schema.py
transform/vendor/gql/transport/phoenix_channel_websockets.py
transform/vendor/gql/transport/requests.py
transform/vendor/gql/transport/transport.py
transform/vendor/gql/transport/websockets.py
transform/vendor/gql/transport/websockets_base.py
transform/vendor/gql/utilities/__init__.py
transform/vendor/gql/utilities/build_client_schema.py
transform/vendor/gql/utilities/get_introspection_query_ast.py
transform/vendor/gql/utilities/parse_result.py
transform/vendor/gql/utilities/serialize_variable_values.py
transform/vendor/gql/utilities/update_schema_enum.py
transform/vendor/gql/utilities/update_schema_scalars.py
transform/vendor/gql/utils.py
transform/vendor/graphql3/__init__.py
transform/vendor/graphql3/error/__init__.py
transform/vendor/graphql3/error/graphql_error.py
transform/vendor/graphql3/error/located_error.py
transform/vendor/graphql3/error/syntax_error.py
transform/vendor/graphql3/execution/__init__.py
transform/vendor/graphql3/execution/collect_fields.py
transform/vendor/graphql3/execution/execute.py
transform/vendor/graphql3/execution/map_async_iterator.py
transform/vendor/graphql3/execution/middleware.py
transform/vendor/graphql_core-3.2.0.dist-info/INSTALLER
transform/vendor/graphql_core-3.2.0.dist-info/LICENSE
transform/vendor/graphql_core-3.2.0.dist-info/METADATA
transform/vendor/graphql_core-3.2.0.dist-info/RECORD
transform/vendor/graphql_core-3.2.0.dist-info/WHEEL
transform/vendor/graphql_core-3.2.0.dist-info/top_level.txt
transform/vendor/idna-3.3.dist-info/INSTALLER
transform/vendor/idna-3.3.dist-info/LICENSE.md
transform/vendor/idna-3.3.dist-info/METADATA
transform/vendor/idna-3.3.dist-info/RECORD
transform/vendor/idna-3.3.dist-info/WHEEL
transform/vendor/idna-3.3.dist-info/top_level.txt
transform/vendor/multidict-6.0.2.dist-info/INSTALLER
transform/vendor/multidict-6.0.2.dist-info/LICENSE
transform/vendor/multidict-6.0.2.dist-info/METADATA
transform/vendor/multidict-6.0.2.dist-info/RECORD
transform/vendor/multidict-6.0.2.dist-info/WHEEL
transform/vendor/multidict-6.0.2.dist-info/top_level.txt
transform/vendor/yarl-1.7.2.dist-info/INSTALLER
transform/vendor/yarl-1.7.2.dist-info/LICENSE
transform/vendor/yarl-1.7.2.dist-info/METADATA
transform/vendor/yarl-1.7.2.dist-info/RECORD
transform/vendor/yarl-1.7.2.dist-info/WHEEL
transform/vendor/yarl-1.7.2.dist-info/top_level.txt
transform-1.0.19rc2.dist-info/entry_points.txt
transform-1.0.19rc2.dist-info/WHEEL
transform-1.0.19rc2.dist-info/METADATA
transform-1.0.19rc2.dist-info/RECORD
