Metadata-Version: 2.1
Name: transform
Version: 1.0.19rc2
Summary: Transform MQL Client Library
Author: Your Name
Author-email: you@example.com
Requires-Python: >=3.8,<3.10
Classifier: Programming Language :: Python :: 3
Classifier: Programming Language :: Python :: 3.8
Classifier: Programming Language :: Python :: 3.9
Requires-Dist: GitPython (>=3.1.27,<4.0.0)
Requires-Dist: PyYAML (>=6.0,<7.0)
Requires-Dist: aiohttp (>=3.8.1,<4.0.0)
Requires-Dist: arrow (>=1.2.2,<2.0.0)
Requires-Dist: click (==7.1.2)
Requires-Dist: log-symbols (>=0.0.14,<0.0.15)
Requires-Dist: pandas (>=1.4.1,<2.0.0)
Requires-Dist: requests (>=2.27.1,<3.0.0)
Requires-Dist: tabulate (>=0.8.9,<0.9.0)
Requires-Dist: transform-tools (>=1.0.2,<2.0.0)
Requires-Dist: update-checker (>=0.18.0,<0.19.0)
